somador_subtrator/__init__.py
somador_subtrator/calculadora_jose.py
somador_subtrator-0.1.0.dist-info/LICENSE
somador_subtrator-0.1.0.dist-info/METADATA
somador_subtrator-0.1.0.dist-info/WHEEL
somador_subtrator-0.1.0.dist-info/top_level.txt
somador_subtrator-0.1.0.dist-info/RECORD
