Metadata-Version: 2.1
Name: somador-subtrator
Version: 0.1.0
Summary: Uma calculadora simples para somar e subtrair.
Author: José Eduardo
Author-email: josedumoura@gmail.com
Requires-Python: >=3.6
License-File: LICENSE
